{"generatedAt":1727896495512,"generateTime":83,"contents":[{"_path":"/","_dir":"","_draft":false,"_partial":false,"_locale":"","title":"Legion Tanks","description":" Сайт в разработке","body":{"type":"root","children":[{"type":"element","tag":"h1","props":{"id":"legion-tanks"},"children":[{"type":"text","value":"Legion Tanks"}]},{"type":"element","tag":"p","props":{},"children":[{"type":"element","tag":"icon","props":{"name":"mdi:hammer-screwdriver"},"children":[]},{"type":"text","value":" Сайт в разработке"}]}],"toc":{"title":"","searchDepth":2,"depth":2,"links":[]}},"_type":"markdown","_id":"content:1.index.md","_source":"content","_file":"1.index.md","_stem":"1.index","_extension":"md"},{"_path":"/about","_dir":"","_draft":false,"_partial":false,"_locale":"","title":"About","description":"This site is an official site project Legion Tanks.","navigation":{"title":"About"},"layout":"full-width","head":{"description":"Official site LegionTanks."},"body":{"type":"root","children":[{"type":"element","tag":"h1","props":{"id":"about"},"children":[{"type":"text","value":"About"}]},{"type":"element","tag":"p","props":{},"children":[{"type":"text","value":"This site is an official site project Legion Tanks."}]},{"type":"element","tag":"icon","props":{"name":"line-md:chat-round-aler"},"children":[]}],"toc":{"title":"","searchDepth":2,"depth":2,"links":[]}},"_type":"markdown","_id":"content:2.about.md","_source":"content","_file":"2.about.md","_stem":"2.about","_extension":"md"},{"_path":"/futures","_dir":"","_draft":false,"_partial":false,"_locale":"","title":"Futures","description":"You can see the game features and their status in the following tables.","body":{"type":"root","children":[{"type":"element","tag":"h1","props":{"id":"futures"},"children":[{"type":"text","value":"Futures"}]},{"type":"element","tag":"p","props":{},"children":[{"type":"text","value":"You can see the game features and their status in the following tables."}]},{"type":"element","tag":"p","props":{},"children":[{"type":"text","value":"✅ The feature is fully implemented and working as intended."}]},{"type":"element","tag":"p","props":{},"children":[{"type":"text","value":"⚒️ Work is currently being done on the feature."}]},{"type":"element","tag":"p","props":{},"children":[{"type":"text","value":"🚧 A prototype version of the feature is implemented. For ex"}]}],"toc":{"title":"","searchDepth":2,"depth":2,"links":[]}},"_type":"markdown","_id":"content:3.futures.md","_source":"content","_file":"3.futures.md","_stem":"3.futures","_extension":"md"}],"navigation":[{"title":"Legion Tanks","_path":"/"},{"title":"About","_path":"/about","layout":"full-width"},{"title":"Futures","_path":"/futures"}]}